geoweaver_cwl/__init__.py
geoweaver_cwl/translator.py
geoweaver_cwl-0.0.1.dist-info/LICENSE.txt
geoweaver_cwl-0.0.1.dist-info/METADATA
geoweaver_cwl-0.0.1.dist-info/WHEEL
geoweaver_cwl-0.0.1.dist-info/top_level.txt
geoweaver_cwl-0.0.1.dist-info/RECORD
