Metadata-Version: 2.1
Name: geoweaver_cwl
Version: 0.0.1
Summary: A tool wrapper to translate Geoweaver AI workflows into Common Workflow Language (CWL)
Home-page: https://github.com/amrutakale08/geoweaver_cwl
Author: Amruta Kale
Author-email: akale@uidaho.edu
Project-URL: Bug Tracker, https://github.com/pypa/sampleproject/issues
Classifier: Programming Language :: Python :: 3
Classifier: License :: OSI Approved :: MIT License
Classifier: Operating System :: OS Independent
Requires-Python: >=3.6
License-File: LICENSE.txt
